easyflake/__init__.py
easyflake/__main__.py
easyflake/clock.py
easyflake/config.py
easyflake/easyflake.py
easyflake/exceptions.py
easyflake/grpc/__init__.py
easyflake/grpc/sequence_pb2.py
easyflake/grpc/sequence_pb2.pyi
easyflake/grpc/sequence_pb2_grpc.py
easyflake/logging.py
easyflake/node/__init__.py
easyflake/node/base.py
easyflake/node/file.py
easyflake/node/grpc.py
easyflake/sequence.py
easyflake/utils/__init__.py
easyflake/utils/contextlib.py
easyflake/utils/singleton.py
easyflake-0.3.1.dist-info/LICENSE
easyflake-0.3.1.dist-info/METADATA
easyflake-0.3.1.dist-info/WHEEL
easyflake-0.3.1.dist-info/entry_points.txt
easyflake-0.3.1.dist-info/RECORD
