Metadata-Version: 2.1
Name: easyflake
Version: 0.3.1
Summary: EasyFlake is a Python package for generating 64-bit IDs similar to Snowflake or Sonyflake.
Home-page: https://github.com/tsuperis/easyflake
Keywords: snowflake,sonyflake,easyflake
Author: Takeru Furuse
Author-email: tsuperis@gmail.com
Requires-Python: >=3.8,<4.0
Classifier: Development Status :: 4 - Beta
Classifier: Programming Language :: Python :: 3
Classifier: Programming Language :: Python :: 3.8
Classifier: Programming Language :: Python :: 3.9
Classifier: Programming Language :: Python :: 3.10
Classifier: Programming Language :: Python :: 3.11
Classifier: Topic :: Software Development :: Libraries :: Python Modules
Classifier: Topic :: Utilities
Requires-Dist: click (>=8.1.3,<9.0.0)
Requires-Dist: grpcio (>=1.51.3,<2.0.0)
Requires-Dist: grpcio-health-checking (>=1.51.3,<2.0.0)
Requires-Dist: lockfile (>=0.12.2,<0.13.0)
Requires-Dist: python-daemon (>=2.3.2,<3.0.0) ; sys_platform == "linux" or sys_platform == "darwin"
